etrc/__init__.py
etrc/_modidx.py
etrc/atyp.py
etrc/cons.py
etrc/emod.py
etrc/enum.py
etrc/kwds.py
etrc/meta.py
etrc/solv.py
etrc/util.py
etrc-0.0.21.dist-info/LICENSE
etrc-0.0.21.dist-info/METADATA
etrc-0.0.21.dist-info/WHEEL
etrc-0.0.21.dist-info/entry_points.txt
etrc-0.0.21.dist-info/top_level.txt
etrc-0.0.21.dist-info/RECORD
