Metadata-Version: 2.1
Name: etrc
Version: 0.0.21
Summary: PyTorch Enumerations
Home-page: https://github.com/dsm-72/etrc
Author: dsm-72
Author-email: sumner.magruder@yale.edu
License: Apache Software License 2.0
Keywords: python py torch pytorch lightning pl trc enum enums enumeration
Classifier: Development Status :: 4 - Beta
Classifier: Intended Audience :: Developers
Classifier: Natural Language :: English
Classifier: Programming Language :: Python :: 3.11
Classifier: License :: OSI Approved :: Apache Software License
Requires-Python: >=3.11
License-File: LICENSE
Requires-Dist: nchr
Requires-Dist: nlit
Requires-Dist: quac
Requires-Dist: sigr
Requires-Dist: dref
Requires-Dist: chck
Requires-Dist: astr
Requires-Dist: dstr
Requires-Dist: uscr
Requires-Dist: atup
Requires-Dist: asto
Provides-Extra: dev
Requires-Dist: numpy ; extra == 'dev'
Requires-Dist: pandas ; extra == 'dev'
Requires-Dist: matplotlib ; extra == 'dev'
Requires-Dist: torch ; extra == 'dev'
Requires-Dist: pytorch-lightning ; extra == 'dev'
Requires-Dist: torchvision ; extra == 'dev'
Requires-Dist: pot ; extra == 'dev'
